arbeitszeit/__init__.py
arbeitszeit/__main__.py
arbeitszeit/main.py
arbeitszeit-0.1.4.dist-info/LICENSE
arbeitszeit-0.1.4.dist-info/METADATA
arbeitszeit-0.1.4.dist-info/WHEEL
arbeitszeit-0.1.4.dist-info/entry_points.txt
arbeitszeit-0.1.4.dist-info/RECORD
