Metadata-Version: 2.1
Name: arbeitszeit
Version: 0.1.4
Summary: Track your worktime.
Home-page: https://github.com/david-haerer/arbeitszeit
License: MIT
Author: David Härer
Author-email: david@haerer.dev
Requires-Python: >=3.11,<4.0
Classifier: License :: OSI Approved :: MIT License
Classifier: Programming Language :: Python :: 3
Classifier: Programming Language :: Python :: 3.11
Classifier: Programming Language :: Python :: 3.12
Requires-Dist: appdirs (>=1.4.4,<2.0.0)
Requires-Dist: isoweek (>=1.3.3,<2.0.0)
Requires-Dist: pydantic (>=2.5.1,<3.0.0)
Requires-Dist: pyyaml (>=6.0.1,<7.0.0)
Requires-Dist: typer (>=0.9.0,<0.10.0)
Project-URL: Repository, https://github.com/david-haerer/arbeitszeit
